different_wrapping/__init__.py
different_wrapping/challenge.py
different_wrapping/cli.py
different_wrapping/compose.py
different_wrapping/gateway.py
different_wrapping/ingress.py
different_wrapping/metadata.py
different_wrapping/utils.py
different_wrapping/yamlyaml.py
different_wrapping-1.0.29.dist-info/licenses/LICENSE
different_wrapping-1.0.29.dist-info/METADATA
different_wrapping-1.0.29.dist-info/WHEEL
different_wrapping-1.0.29.dist-info/entry_points.txt
different_wrapping-1.0.29.dist-info/top_level.txt
different_wrapping-1.0.29.dist-info/RECORD
