Metadata-Version: 2.4
Name: different_wrapping
Version: 1.0.29
Summary: Simple k8s yaml generator for CTF challenges
Author-email: petterroea <spam+pypi@petterroea.com>
Classifier: Programming Language :: Python :: 3
Classifier: License :: OSI Approved :: GNU General Public License v3 (GPLv3)
Requires-Python: >=3.7
License-File: LICENSE
Requires-Dist: PyYAML
Dynamic: license-file
